setup.py
transmission/__init__.py
transmission/json_utils.py
transmission_fluid.egg-info/PKG-INFO
transmission_fluid.egg-info/SOURCES.txt
transmission_fluid.egg-info/dependency_links.txt
transmission_fluid.egg-info/requires.txt
transmission_fluid.egg-info/top_level.txt