Metadata-Version: 1.1
Name: transmission-fluid
Version: 0.4
Summary: A Python wrapper for Transmission's RPC interface
Home-page: https://github.com/edavis/transmission-fluid
Author: Eric Davis
Author-email: ed@npri.org
License: UNKNOWN
Download-URL: http://pypi.python.org/pypi/transmission-fluid
Platform: UNKNOWN
Classifier: Development Status :: 4 - Beta
Classifier: Intended Audience :: Developers
Classifier: License :: OSI Approved :: MIT License
Classifier: Programming Language :: Python
Classifier: Topic :: Software Development :: Libraries
